bitoli/__init__.py
bitoli/bitoli.py
bitoli-0.1.1.dist-info/LICENSE.txt
bitoli-0.1.1.dist-info/METADATA
bitoli-0.1.1.dist-info/WHEEL
bitoli-0.1.1.dist-info/top_level.txt
bitoli-0.1.1.dist-info/RECORD
