Metadata-Version: 2.1
Name: bitoli
Version: 0.1.1
Summary: Adaptive compression and encryption of data
Home-page: https://github.com/retrotee/bitoli
Author: retrotee
Author-email: 
Classifier: Programming Language :: Python :: 3
Classifier: License :: OSI Approved :: MIT License
Classifier: Operating System :: OS Independent
Requires-Python: >=3.6
License-File: LICENSE.txt
Requires-Dist: cryptography >=3.4.7
